LICENSE
dictattr/__init__.py
dictattr/py.typed
python_dictattr-0.0.3.dist-info/LICENSE
python_dictattr-0.0.3.dist-info/METADATA
python_dictattr-0.0.3.dist-info/WHEEL
python_dictattr-0.0.3.dist-info/RECORD
